pyaz/__init__.py
pyaz/cli.py
pyaz/version.py
pyaz-0.0.1.dist-info/LICENSE
pyaz-0.0.1.dist-info/METADATA
pyaz-0.0.1.dist-info/WHEEL
pyaz-0.0.1.dist-info/entry_points.txt
pyaz-0.0.1.dist-info/top_level.txt
pyaz-0.0.1.dist-info/RECORD
