Metadata-Version: 2.1
Name: pyaz
Version: 0.0.1
Summary: Pythonic Azure tools
Home-page: https://github.com/ivangeorgiev/pyaz
Author: Ivan Georgiev
License: UNKNOWN
Platform: UNKNOWN
Classifier: Programming Language :: Python :: 3
Classifier: License :: OSI Approved :: MIT License
Classifier: Operating System :: OS Independent
Requires-Python: >=3.6
Requires-Dist: click
Requires-Dist: python-dotenv
